coffeefetch/__init__.py
coffeefetch/__main__.py
coffeefetch/fetch.py
coffeefetch/quotes/quotes.txt
coffeefetch-1.3.0.dist-info/METADATA
coffeefetch-1.3.0.dist-info/WHEEL
coffeefetch-1.3.0.dist-info/licenses/LICENCE
coffeefetch-1.3.0.dist-info/RECORD
