Metadata-Version: 2.1
Name: coffeefetch
Version: 1.3.0
Summary: A lightweight system information grabber written in Python
Project-URL: Homepage, https://github.com/TeaPixl/CoffeeFetch
Project-URL: Bug Tracker, https://github.com/TeaPixl/CoffeeFetch/issues
Author-email: Logan Allen <ltallen392@gmail.com>
License-File: LICENCE
Classifier: License :: OSI Approved :: MIT License
Classifier: Operating System :: POSIX :: Linux
Classifier: Programming Language :: Python :: 3
Requires-Python: >=3.7
